[{"id":"rhinedottir","name":"Rhinedottir","description":"Genshin Impact damage calculator and simulator.","client":"Gregory Mcmillan","industry":"Gaming","uri":"rhinedottir","liveUrl":"https://rhinedottir.com","repository":"https://github.com/sipofnightshade/rhinedottir","image":"hero.webp","featuredImage":"featured.webp","roles":["designer","developer"],"platforms":["Web","Mobile","PWA"],"technologies":["sveltekit","typescript","tailwindcss"],"keywords":["genshin impact","damage calculator","genshin simulator"],"featured":true,"sections":[{"type":"image","image":"1.webp","alt":"Rhinedottir section 1 image."},{"type":"text","title":"Project Overview","content":"Lorem ipsum dolor sit amet, consectetur adipiscing elit...","footnote":"A large portion of the user base comes from mobile as well as consoles. This makes mobile versions of this application pivotal."},{"type":"image","image":"2.webp","alt":"Rhinedottir section 2 image"},{"type":"image","image":"3.webp","alt":"Rhinedottir section 3 image"}]},{"id":"project2","name":"Project 2","description":"A cutting-edge e-commerce platform designed to revolutionize online shopping.","client":"Acme Corporation","industry":"Gaming","uri":"project2","liveUrl":"https://project2.com","repository":"https://github.com/user/project2","image":"hero.webp","featuredImage":"featured.webp","roles":["designer","developer"],"platforms":["Web","Mobile","PWA"],"technologies":["sveltekit","typescript"],"keywords":["e-commerce","web development","mern stack"],"featured":true,"sections":[{"type":"text","title":"Project Overview","content":"Lorem ipsum dolor sit amet, consectetur adipiscing elit...","footnote":null},{"type":"image","image":"project2_section1.webp","alt":"Project 2 Section 1 Image"},{"type":"gallery","images":["project2_gallery1.webp","project2_gallery2.webp"],"caption":"Project Gallery"},{"type":"video","url":"https://www.youtube.com/watch?v=examplevideo","title":"Project Demo"},{"type":"testimonial","quote":"This project has exceeded our expectations.","author":"Client Name","position":"Client Title"}]},{"id":"project3","name":"Project 3","description":"A cutting-edge e-commerce platform designed to revolutionize online shopping.","client":"Acme Corporation","industry":"Gaming","uri":"project3","liveUrl":"https://project3.com","repository":"https://github.com/user/project3","image":"hero.webp","featuredImage":"featured.webp","roles":["designer","developer"],"platforms":["Web","Mobile","PWA"],"technologies":["sveltekit","typescript"],"keywords":["e-commerce","web development","mern stack"],"featured":true,"sections":[{"type":"text","title":"Project Overview","content":"Lorem ipsum dolor sit amet, consectetur adipiscing elit...","footnote":null},{"type":"image","image":"project3_section1.webp","alt":"Project 3 Section 1 Image"},{"type":"gallery","images":["project3_gallery1.webp","project3_gallery2.webp"],"caption":"Project Gallery"},{"type":"video","url":"https://www.youtube.com/watch?v=examplevideo","title":"Project Demo"},{"type":"testimonial","quote":"This project has exceeded our expectations.","author":"Client Name","position":"Client Title"}]}]